socklocks.py
socklocks-0.1.0.dist-info/LICENSE
socklocks-0.1.0.dist-info/METADATA
socklocks-0.1.0.dist-info/WHEEL
socklocks-0.1.0.dist-info/top_level.txt
socklocks-0.1.0.dist-info/RECORD
