Metadata-Version: 2.1
Name: socklocks
Version: 0.1.0
Summary: Library of Python locks that use sockets to keep processes synchronized.
Home-page: https://github.com/JustinTArthur/socklocks
Author: Justin Turner Arthur
Author-email: justinarthur@gmail.com
License: Apache License 2.0
Keywords: query string,querystring,URL,parser
Platform: UNKNOWN
Classifier: Programming Language :: Python
Classifier: Intended Audience :: Developers
Classifier: License :: OSI Approved :: MIT License
Classifier: Topic :: Software Development :: Libraries :: Python Modules
Classifier: Environment :: Web Environment
